{
    "config": {
        "head": {
            "title": "Nuxt Starter | ",
            "description": "Default Nuxt Starter Description",
            "fb": "cmacmillanmarin",
            "tw": "cmacmillanmarin"
        },
        "routes": {
            "home": "/",
            "dynamic": "/dynamic",
            "webgl": "/webgl",
            "threejs": "/threejs"
        }
    },
    "header": {},
    "pages": {
        "home": {
            "head": {
                "title": "Home",
                "description": "Home Description"
            },
            "images": [
                "static-assets-base",
                "static-assets-base64"
            ]
        },
        "webgl": {
            "head": {
                "title": "WebGL",
                "description": "WebGL Description"
            },
            "image": "static-assets-base64"
        },
        "threejs": {
            "head": {
                "title": "Three js",
                "description": "Three js Description"
            },
            "image": "static-assets-base64"
        }
    },
    "assets": {
        "static-assets-base64": {
            "src": "assets/img/base64.jpg",
            "alt": "base64",
            "ratio": "1x1"
        },
        "static-assets-base": {
            "src": "assets/img/base.jpg",
            "alt": "base",
            "ratio": "1x1"
        }
    }
}